ssa/__init__.py
ssa/direct.py
ssa/engine.py
ssa/model.py
ssa/output.py
ssa/plot.py
ssa/result.py
ssa/util.py
ssa/version.py
ssa-0.0.3.dist-info/LICENSE
ssa-0.0.3.dist-info/METADATA
ssa-0.0.3.dist-info/WHEEL
ssa-0.0.3.dist-info/top_level.txt
ssa-0.0.3.dist-info/RECORD
