Metadata-Version: 2.1
Name: ssa
Version: 0.0.3
Summary: Stochastic Simulation Algorithms
Home-page: https://github.com/yannikschaelte/ssa
Author: The SSA developers
Author-email: yannik.schaelte@gmail.com
Maintainer: The SSA developers
Maintainer-email: yannik.schaelte@gmail.com
License: BSD-3-Clause
Download-URL: https://github.com/yannikschaelte/ssa/releases
Project-URL: Bug Tracker, https://github.com/yannikschaelte/ssa/issues
Platform: UNKNOWN
Requires-Python: >=3.6
Requires-Dist: numpy (>=1.19.1)
Requires-Dist: scipy (>=1.5.2)
Requires-Dist: pandas (>=1.2.0)
